MANIFEST.in
README.md
VERSION
requirements.txt
setup.py
scripts/purge-namespace.py
webiam/__init__.py
webiam/conftest.py
webiam/package.json
webiam.egg-info/PKG-INFO
webiam.egg-info/SOURCES.txt
webiam.egg-info/dependency_links.txt
webiam.egg-info/requires.txt
webiam.egg-info/top_level.txt
webiam/app/__init__.py
webiam/app/asgi.py
webiam/app/endpoints/__init__.py
webiam/app/endpoints/consent.py
webiam/app/endpoints/onboarding.py
webiam/app/endpoints/models/__init__.py
webiam/app/endpoints/models/beginonboardrequest.py
webiam/app/endpoints/models/grantconsentrequest.py
webiam/canon/__init__.py
webiam/canon/fingerprint.py
webiam/canon/fingerprintbrowser.py
webiam/canon/fingerprintconfidence.py
webiam/canon/fingerprintlocation.py
webiam/canon/fingerprintlocationcity.py
webiam/canon/fingerprintlocationcontinent.py
webiam/canon/fingerprintlocationcountry.py
webiam/canon/fingerprintreference.py
webiam/canon/fingerprintuseragent.py
webiam/infra/__init__.py
webiam/infra/fingerprintresolver.py
webiam/runtime/__init__.py
webiam/runtime/boot.py
webiam/runtime/settings/__init__.py
webiam/runtime/settings/defaults.py
webiam/runtime/settings/ioc.py
webiam/runtime/settings/local.py
webiam/runtime/settings/staging.py